studcamp_yandex_hse/__init__.py
studcamp_yandex_hse/models/__init__.py
studcamp_yandex_hse/models/attention_based_model/__init__.py
studcamp_yandex_hse/models/attention_based_model/attention_extractor.py
studcamp_yandex_hse/models/attention_based_model/tags_extractor.py
studcamp_yandex_hse/models/bart_based_model/__init__.py
studcamp_yandex_hse/models/bart_based_model/tag_sum_extractor.py
studcamp_yandex_hse/models/base_extractor.py
studcamp_yandex_hse/models/clusterizer_based_model/__init__.py
studcamp_yandex_hse/models/clusterizer_based_model/clusterizer.py
studcamp_yandex_hse/models/clusterizer_based_model/faiss.py
studcamp_yandex_hse/models/metrics.py
studcamp_yandex_hse/models/rake_based_model/__init__.py
studcamp_yandex_hse/models/rake_based_model/keyphrases_extractor.py
studcamp_yandex_hse/models/rake_based_model/tags_extractor.py
studcamp_yandex_hse/models/rut5_based_model/__init__.py
studcamp_yandex_hse/models/rut5_based_model/rut5_extractor.py
studcamp_yandex_hse/processing/__init__.py
studcamp_yandex_hse/processing/embedder/__init__.py
studcamp_yandex_hse/processing/embedder/base_embedder.py
studcamp_yandex_hse/processing/embedder/fasttext_embedder.py
studcamp_yandex_hse/processing/embedder/rubert_embedder.py
studcamp_yandex_hse/processing/normalizers/__init__.py
studcamp_yandex_hse/processing/normalizers/base_normalizer.py
studcamp_yandex_hse/processing/normalizers/nouns_keeper.py
studcamp_yandex_hse/processing/normalizers/pipe.py
studcamp_yandex_hse/processing/normalizers/punctuation_deleter.py
studcamp_yandex_hse/processing/normalizers/stopwords_deleter.py
studcamp_yandex_hse/processing/ranker/__init__.py
studcamp_yandex_hse/processing/ranker/base_ranker.py
studcamp_yandex_hse/processing/ranker/max_distance_ranker.py
studcamp_yandex_hse/processing/ranker/text_sim_ranker.py
studcamp_yandex_hse/processing/summarizator/__init__.py
studcamp_yandex_hse/processing/summarizator/bart_summarization.py
studcamp_yandex_hse/processing/utils.py
studcamp_yandex_hse-0.1.2.dist-info/METADATA
studcamp_yandex_hse-0.1.2.dist-info/WHEEL
studcamp_yandex_hse-0.1.2.dist-info/RECORD
