Metadata-Version: 2.1
Name: studcamp-yandex-hse
Version: 0.1.2
Summary: Text-tagging project within Yandex x HSE StudCamp event
License: MIT
Author: deniskazhekin
Author-email: deniskazhekin@yandex.ru
Requires-Python: >=3.10,<3.12
Classifier: License :: OSI Approved :: MIT License
Classifier: Programming Language :: Python :: 3
Classifier: Programming Language :: Python :: 3.10
Classifier: Programming Language :: Python :: 3.11
Requires-Dist: accelerate (>=0.29.3,<0.30.0)
Requires-Dist: dvc (>=3.50.1,<4.0.0)
Requires-Dist: dvc-gdrive (>=3.0.1,<4.0.0)
Requires-Dist: faiss-cpu (>=1.8.0,<2.0.0)
Requires-Dist: fasttext-wheel (>=0.9.2,<0.10.0)
Requires-Dist: gdown (>=5.1.0,<6.0.0)
Requires-Dist: nltk (>=3.8.1,<4.0.0)
Requires-Dist: peft (>=0.10.0,<0.11.0)
Requires-Dist: pre-commit (>=3.7.0,<4.0.0)
Requires-Dist: pymorphy2 (>=0.9.1,<0.10.0)
Requires-Dist: rake-nltk (>=1.0.6,<2.0.0)
Requires-Dist: scipy (==1.10.1)
Requires-Dist: sentence-transformers (>=2.7.0,<3.0.0)
Requires-Dist: sentencepiece (>=0.2.0,<0.3.0)
Requires-Dist: streamlit (>=1.33.0,<2.0.0)
Requires-Dist: transformers (>=4.40.1,<5.0.0)
